trytond/modules/stock_kit/1inventory.py
trytond/modules/stock_kit/1product.py
trytond/modules/stock_kit/__init__.py
trytond/modules/stock_kit/inventory.py
trytond/modules/stock_kit/message.xml
trytond/modules/stock_kit/product.py
trytond/modules/stock_kit/product.xml
trytond/modules/stock_kit/tryton.cfg
trytond/modules/stock_kit/locale/ca_ES.po
trytond/modules/stock_kit/locale/de.po
trytond/modules/stock_kit/locale/es_ES.po
trytond/modules/stock_kit/tests/__init__.py
trytond/modules/stock_kit/tests/test_stock_kit.py
trytond/modules/stock_kit/view/product_form.xml
m9s_stock_kit-5.2.2.dist-info/LICENSE
m9s_stock_kit-5.2.2.dist-info/METADATA
m9s_stock_kit-5.2.2.dist-info/WHEEL
m9s_stock_kit-5.2.2.dist-info/entry_points.txt
m9s_stock_kit-5.2.2.dist-info/top_level.txt
m9s_stock_kit-5.2.2.dist-info/RECORD
